trigon/__init__.py
trigon/cli/__init__.py
trigon/cli/commands/__init__.py
trigon/cli/commands/database.py
trigon/cli/commands/migrations.py
trigon/cli/manage.py
trigon/contrib/__init__.py
trigon/contrib/plugins/__init__.py
trigon/contrib/plugins/database/__init__.py
trigon/contrib/plugins/plugin.py
trigon/contrib/plugins/plugin_builder.py
trigon/contrib/repository.py
trigon/contrib/service.py
trigon/core/__init__.py
trigon/core/controller/__init__.py
trigon/core/controller/controller.py
trigon/core/controller/http.py
trigon/core/controller/result.py
trigon/core/controller/route.py
trigon/core/dependency_injection.py
trigon/core/event_handler.py
trigon/core/logging/__init__.py
trigon/core/logging/handlers.py
trigon/core/logging/logger_builder.py
trigon/core/middleware.py
trigon/core/settings.py
trigon/helpers/__init__.py
trigon/helpers/resolution.py
trigon/middlewares/__init__.py
trigon/middlewares/correlation_id.py
trigon/middlewares/logging.py
trigon/py.typed
trigon/trigon.py
trigon-0.2.0.dist-info/LICENSE
trigon-0.2.0.dist-info/METADATA
trigon-0.2.0.dist-info/WHEEL
trigon-0.2.0.dist-info/entry_points.txt
trigon-0.2.0.dist-info/RECORD
