Metadata-Version: 2.1
Name: trigon
Version: 0.2.0
Summary: A batteries-included python web framework
Home-page: https://billsioros.github.io/trigon
License: MIT
Author: Vasilis Sioros
Author-email: billsioros97@gmail.com
Requires-Python: >=3.8,<4.0
Classifier: License :: OSI Approved :: MIT License
Classifier: Programming Language :: Python
Classifier: Programming Language :: Python :: 3
Classifier: Programming Language :: Python :: 3.8
Classifier: Programming Language :: Python :: 3.9
Classifier: Programming Language :: Python :: 3.10
Classifier: Programming Language :: Python :: 3.11
Classifier: Programming Language :: Python :: 3 :: Only
Requires-Dist: alembic (>=1.12.0,<2.0.0)
Requires-Dist: fastapi (>=0.103.1,<0.104.0)
Requires-Dist: lagom (>=2.4.1,<3.0.0)
Requires-Dist: loguru (>=0.7.1,<0.8.0)
Requires-Dist: pydantic (>=2.3.0,<3.0.0)
Requires-Dist: pydantic-settings (>=2.0.3,<3.0.0)
Requires-Dist: sqlalchemy (>=2.0.20,<3.0.0)
Requires-Dist: typer (>=0.9.0,<0.10.0)
Requires-Dist: uvicorn[standard] (>=0.23.2,<0.24.0)
Project-URL: Bug Tracker, https://github.com/billsioros/trigon/issues
Project-URL: Changelog, https://github.com/billsioros/trigon/releases
Project-URL: Repository, https://github.com/billsioros/trigon
